strawberry_mage/__init__.py
strawberry_mage/backends/__init__.py
strawberry_mage/backends/dataloader/__init__.py
strawberry_mage/backends/sqlalchemy/__init__.py
strawberry_mage/backends/sqlalchemy/backend.py
strawberry_mage/backends/sqlalchemy/models.py
strawberry_mage/backends/sqlalchemy/operations.py
strawberry_mage/backends/sqlalchemy/utils.py
strawberry_mage/core/__init__.py
strawberry_mage/core/backend.py
strawberry_mage/core/models.py
strawberry_mage/core/resolvers/__init__.py
strawberry_mage/core/resolvers/base.py
strawberry_mage/core/resolvers/resolvers.py
strawberry_mage/core/schema.py
strawberry_mage/core/strawberry_types.py
strawberry_mage/core/type_creator.py
strawberry_mage/core/types.py
strawberry_mage/core/types_generated.py
strawberry_mage/core/utils.py
strawberry_graphql_mage-0.0.1a9.dev1657963998.dist-info/WHEEL
strawberry_graphql_mage-0.0.1a9.dev1657963998.dist-info/METADATA
strawberry_graphql_mage-0.0.1a9.dev1657963998.dist-info/RECORD
