Metadata-Version: 2.1
Name: strawberry-graphql-mage
Version: 0.0.1a9.dev1657963998
Summary: An automated, modular, backend-agnostic GraphQL API generator
License: MIT
Author: Vojtěch Dohnal
Author-email: vojdoh@gmail.com
Requires-Python: >=3.8,<4.0
Classifier: Development Status :: 2 - Pre-Alpha
Classifier: Environment :: Web Environment
Classifier: Intended Audience :: Developers
Classifier: License :: OSI Approved :: MIT License
Classifier: Natural Language :: English
Classifier: Operating System :: OS Independent
Classifier: Programming Language :: Python :: 3
Classifier: Programming Language :: Python :: 3.10
Classifier: Programming Language :: Python :: 3.8
Classifier: Programming Language :: Python :: 3.9
Requires-Dist: SQLAlchemy-Utils (>=0.38.2,<0.39.0)
Requires-Dist: SQLAlchemy[asyncio] (>=1.4.25,<2.0.0)
Requires-Dist: aiosqlite (>=0.17.0,<0.18.0)
Requires-Dist: frozendict (>=2.0.6,<3.0.0)
Requires-Dist: inflection (>=0.5.1,<0.6.0)
Requires-Dist: overrides (>=6.1.0,<7.0.0)
Requires-Dist: strawberry-graphql (>0.80.0,<1.0.0)
Project-URL: Homepage, https://github.com/KundaPanda/strawberry-graphql-mage/
